{
  "Links": [
    "get-/projects",
    "post-/projects",
    "post-/projects/user/{user_id}",
    "get-/projects/{id}",
    "put-/projects/{id}",
    "post-/projects/{id}/fork",
    "get-/projects/{id}/forks",
    "post-/projects/{id}/star",
    "post-/projects/{id}/unstar",
    "post-/projects/{id}/archive",
    "post-/projects/{id}/unarchive",
    "post-/projects/{id}/restore",
    "put-/projects/{id}/transfer",
    "get-/users/{user_id}/projects",
    "get-/users/{user_id}/starred_projects"
  ],
  "Permissions": [
    "get-/projects",
    "post-/projects",
    "post-/projects/user/{user_id}",
    "get-/projects/{id}",
    "put-/projects/{id}",
    "post-/projects/{id}/fork",
    "post-/projects/{id}/archive",
    "post-/projects/{id}/unarchive",
    "post-/projects/{id}/restore",
    "put-/projects/{id}/transfer",
    "get-/users/{user_id}/projects",
    "get-/users/{user_id}/starred_projects"
  ],
  "Owner": [
    "get-/projects",
    "post-/projects",
    "post-/projects/user/{user_id}",
    "get-/projects/{id}",
    "put-/projects/{id}",
    "post-/projects/{id}/fork",
    "post-/projects/{id}/archive",
    "post-/projects/{id}/unarchive",
    "post-/projects/{id}/restore",
    "put-/projects/{id}/transfer",
    "get-/users/{user_id}/projects",
    "get-/users/{user_id}/starred_projects"
  ],
  "Statistics": [
    "get-/projects",
    "post-/projects",
    "post-/projects/user/{user_id}",
    "get-/projects/{id}",
    "put-/projects/{id}",
    "post-/projects/{id}/fork",
    "post-/projects/{id}/restore",
    "put-/projects/{id}/transfer",
    "get-/users/{user_id}/projects",
    "get-/users/{user_id}/starred_projects"
  ],
  "GroupAccess": [
    "get-/projects",
    "post-/projects",
    "post-/projects/user/{user_id}",
    "get-/projects/{id}",
    "put-/projects/{id}",
    "post-/projects/{id}/fork",
    "post-/projects/{id}/archive",
    "post-/projects/{id}/unarchive",
    "post-/projects/{id}/restore",
    "put-/projects/{id}/transfer",
    "get-/users/{user_id}/projects",
    "get-/users/{user_id}/starred_projects"
  ],
  "SharedWithGroups": [
    "get-/projects",
    "post-/projects",
    "post-/projects/user/{user_id}",
    "get-/projects/{id}",
    "put-/projects/{id}",
    "post-/projects/{id}/fork",
    "get-/projects/{id}/forks",
    "post-/projects/{id}/star",
    "post-/projects/{id}/unstar",
    "post-/projects/{id}/archive",
    "post-/projects/{id}/unarchive",
    "post-/projects/{id}/restore",
    "put-/projects/{id}/transfer",
    "get-/users/{user_id}/projects",
    "get-/users/{user_id}/starred_projects"
  ],
  "ProjectAccess": [
    "get-/projects",
    "post-/projects",
    "post-/projects/user/{user_id}",
    "get-/projects/{id}",
    "put-/projects/{id}",
    "post-/projects/{id}/fork",
    "post-/projects/{id}/archive",
    "post-/projects/{id}/unarchive",
    "post-/projects/{id}/restore",
    "put-/projects/{id}/transfer",
    "get-/users/{user_id}/projects",
    "get-/users/{user_id}/starred_projects"
  ],
  "BasicProjectDetails": [
    "get-/projects",
    "post-/projects",
    "post-/projects/user/{user_id}",
    "put-/projects/{id}",
    "post-/projects/{id}/fork",
    "post-/projects/{id}/restore",
    "get-/users/{user_id}/projects",
    "get-/users/{user_id}/starred_projects"
  ],
  "Namespace": [
    "get-/projects",
    "post-/projects",
    "post-/projects/user/{user_id}",
    "get-/projects/{id}",
    "put-/projects/{id}",
    "post-/projects/{id}/fork",
    "get-/projects/{id}/forks",
    "post-/projects/{id}/star",
    "post-/projects/{id}/unstar",
    "post-/projects/{id}/archive",
    "post-/projects/{id}/unarchive",
    "post-/projects/{id}/restore",
    "put-/projects/{id}/transfer",
    "get-/users/{user_id}/projects",
    "get-/users/{user_id}/starred_projects"
  ],
  "ProjectWithAcess": [
    "get-/projects/{id}",
    "put-/projects/{id}/transfer"
  ],
  "ContainerExpirationPolicy": [
    "get-/projects/{id}",
    "put-/projects/{id}/transfer"
  ],
  "License": [
    "get-/projects/{id}",
    "post-/projects/{id}/star",
    "post-/projects/{id}/unstar",
    "post-/projects/{id}/archive",
    "post-/projects/{id}/unarchive",
    "put-/projects/{id}/transfer"
  ],
  "ForkedFromProject": [
    "get-/projects/{id}",
    "put-/projects/{id}/transfer"
  ],
  "Author": [
    "get-/projects/{id}/users",
    "get-/projects/{id}/starrers"
  ],
  "Project": [
    "get-/projects/{id}/forks"
  ],
  "StarProject": [
    "post-/projects/{id}/star",
    "post-/projects/{id}/unstar"
  ],
  "Starrer": [
    "get-/projects/{id}/starrers"
  ],
  "Language": [
    "get-/projects/{id}/languages"
  ],
  "ArchiveProject": [
    "post-/projects/{id}/archive",
    "post-/projects/{id}/unarchive"
  ],
  "File": [
    "post-/projects/{id}/uploads"
  ],
  "ProjectGroupLink": [
    "post-/projects/{id}/share"
  ],
  "ProjectHook": [
    "get-/projects/{id}/hooks",
    "post-/projects/{id}/hooks",
    "get-/projects/{id}/hooks/{hook_id}",
    "put-/projects/{id}/hooks/{hook_id}",
    "delete-/projects/{id}/hooks/{hook_id}"
  ]
}