{
  "AmendmentSearchItem": [
    "get-/api/v1/Bills/{billId}/Stages/{billStageId}/Amendments"
  ],
  "AmendmentMember": [
    "get-/api/v1/Bills/{billId}/Stages/{billStageId}/Amendments",
    "get-/api/v1/Bills/{billId}/Stages/{billStageId}/Amendments/{amendmentId}",
    "get-/api/v1/Bills/{billId}/Stages/{billStageId}/PingPongItems",
    "get-/api/v1/Bills/{billId}/Stages/{billStageId}/PingPongItems/{pingPongItemId}"
  ],
  "AmendmentSearchItemSearchResult": [
    "get-/api/v1/Bills/{billId}/Stages/{billStageId}/Amendments"
  ],
  "AmendmentDetail": [
    "get-/api/v1/Bills/{billId}/Stages/{billStageId}/Amendments/{amendmentId}"
  ],
  "AmendmentLine": [
    "get-/api/v1/Bills/{billId}/Stages/{billStageId}/Amendments/{amendmentId}",
    "get-/api/v1/Bills/{billId}/Stages/{billStageId}/PingPongItems/{pingPongItemId}"
  ],
  "NewsArticlesSummary": [
    "get-/api/v1/Bills/{billId}/NewsArticles"
  ],
  "NewsArticlesSummarySearchResult": [
    "get-/api/v1/Bills/{billId}/NewsArticles"
  ],
  "BillType": [
    "get-/api/v1/BillTypes"
  ],
  "BillTypeSearchResult": [
    "get-/api/v1/BillTypes"
  ],
  "BillStageSitting": [
    "get-/api/v1/Bills",
    "get-/api/v1/Bills/{billId}",
    "get-/api/v1/Bills/{billId}/Stages/{billStageId}",
    "get-/api/v1/Bills/{billId}/Stages",
    "get-/api/v1/Sittings"
  ],
  "BillSummarySearchResult": [
    "get-/api/v1/Bills"
  ],
  "BillSummary": [
    "get-/api/v1/Bills"
  ],
  "StageSummary": [
    "get-/api/v1/Bills",
    "get-/api/v1/Bills/{billId}",
    "get-/api/v1/Bills/{billId}/Stages"
  ],
  "Bill": [
    "get-/api/v1/Bills/{billId}"
  ],
  "Member": [
    "get-/api/v1/Bills/{billId}"
  ],
  "Promoter": [
    "get-/api/v1/Bills/{billId}"
  ],
  "Organisation": [
    "get-/api/v1/Bills/{billId}"
  ],
  "BillAgent": [
    "get-/api/v1/Bills/{billId}"
  ],
  "Sponsor": [
    "get-/api/v1/Bills/{billId}"
  ],
  "Committee": [
    "get-/api/v1/Bills/{billId}/Stages/{billStageId}"
  ],
  "BillStageDetails": [
    "get-/api/v1/Bills/{billId}/Stages/{billStageId}"
  ],
  "StageSummarySearchResult": [
    "get-/api/v1/Bills/{billId}/Stages"
  ],
  "PublicationDocument": [
    "get-/api/v1/Publications/{publicationId}/Documents/{documentId}",
    "get-/api/v1/Bills/{billId}/Publications",
    "get-/api/v1/Bills/{billId}/Stages/{stageId}/Publications"
  ],
  "AmendmentSummaryMotionSummaryPingPongItemSearchResult": [
    "get-/api/v1/Bills/{billId}/Stages/{billStageId}/PingPongItems"
  ],
  "AmendmentSummaryMotionSummaryPingPongItem": [
    "get-/api/v1/Bills/{billId}/Stages/{billStageId}/PingPongItems"
  ],
  "PingPongAmendmentSummary": [
    "get-/api/v1/Bills/{billId}/Stages/{billStageId}/PingPongItems"
  ],
  "MotionSummary": [
    "get-/api/v1/Bills/{billId}/Stages/{billStageId}/PingPongItems"
  ],
  "MotionDetail": [
    "get-/api/v1/Bills/{billId}/Stages/{billStageId}/PingPongItems/{pingPongItemId}"
  ],
  "MotionGroup": [
    "get-/api/v1/Bills/{billId}/Stages/{billStageId}/PingPongItems/{pingPongItemId}"
  ],
  "PingPongAmendmentDetail": [
    "get-/api/v1/Bills/{billId}/Stages/{billStageId}/PingPongItems/{pingPongItemId}"
  ],
  "AmendmentDetailMotionDetailPingPongItem": [
    "get-/api/v1/Bills/{billId}/Stages/{billStageId}/PingPongItems/{pingPongItemId}"
  ],
  "AmendmentGroup": [
    "get-/api/v1/Bills/{billId}/Stages/{billStageId}/PingPongItems/{pingPongItemId}"
  ],
  "PingPongAmendment": [
    "get-/api/v1/Bills/{billId}/Stages/{billStageId}/PingPongItems/{pingPongItemId}"
  ],
  "PublicationType": [
    "get-/api/v1/PublicationTypes",
    "get-/api/v1/Bills/{billId}/Publications",
    "get-/api/v1/Bills/{billId}/Stages/{stageId}/Publications"
  ],
  "PublicationTypeSearchResult": [
    "get-/api/v1/PublicationTypes"
  ],
  "PublicationLink": [
    "get-/api/v1/Bills/{billId}/Publications",
    "get-/api/v1/Bills/{billId}/Stages/{stageId}/Publications"
  ],
  "BillPublicationList": [
    "get-/api/v1/Bills/{billId}/Publications"
  ],
  "BillPublication": [
    "get-/api/v1/Bills/{billId}/Publications"
  ],
  "Publication": [
    "get-/api/v1/Bills/{billId}/Stages/{stageId}/Publications"
  ],
  "BillStageSittingPublicationList": [
    "get-/api/v1/Bills/{billId}/Stages/{stageId}/Publications"
  ],
  "BillStagePublicationList": [
    "get-/api/v1/Bills/{billId}/Stages/{stageId}/Publications"
  ],
  "BillStageSittingSearchResult": [
    "get-/api/v1/Sittings"
  ],
  "StageReference": [
    "get-/api/v1/Stages"
  ],
  "StageReferenceSearchResult": [
    "get-/api/v1/Stages"
  ]
}