{
  "delete-/groups/{id}/share/{group_id}": [
    [
      "get-/groups",
      "get-/groups/{id}/hooks/{hook_id}"
    ],
    [
      "post-/groups",
      "get-/groups/{id}/hooks/{hook_id}"
    ]
  ],
  "put-/groups/{id}": [
    [
      "get-/groups",
      "get-/groups/{id}/hooks/{hook_id}"
    ],
    [
      "post-/groups",
      "get-/groups/{id}/hooks/{hook_id}"
    ]
  ],
  "get-/groups": [
    [
      "post-/groups"
    ]
  ],
  "post-/groups/{id}/projects/{project_id}": [
    [
      "get-/groups",
      "post-/groups/{id}/share"
    ],
    [
      "post-/groups",
      "post-/groups/{id}/share"
    ]
  ],
  "get-/groups/{id}/hooks/{hook_id}": [
    [
      "get-/groups"
    ],
    [
      "post-/groups"
    ]
  ],
  "get-/groups/{id}/projects/shared": [
    [
      "get-/groups",
      "post-/groups/{id}/share"
    ],
    [
      "post-/groups",
      "post-/groups/{id}/share"
    ]
  ],
  "get-/groups/{id}/subgroups": [
    [
      "get-/groups"
    ],
    [
      "post-/groups"
    ]
  ],
  "post-/groups/{id}/hooks": [
    [
      "get-/groups",
      "get-/groups/{id}/hooks/{hook_id}"
    ],
    [
      "post-/groups",
      "get-/groups/{id}/hooks/{hook_id}"
    ]
  ],
  "get-/groups/{id}/hooks": [
    [
      "get-/groups",
      "get-/groups/{id}/hooks/{hook_id}"
    ],
    [
      "post-/groups",
      "get-/groups/{id}/hooks/{hook_id}"
    ]
  ],
  "get-/groups/{id}/descendant_groups": [
    [
      "get-/groups"
    ],
    [
      "post-/groups"
    ]
  ],
  "get-/groups/{id}": [
    [
      "get-/groups",
      "get-/groups/{id}/hooks/{hook_id}"
    ],
    [
      "post-/groups",
      "get-/groups/{id}/hooks/{hook_id}"
    ]
  ],
  "delete-/groups/{id}": [
    [
      "get-/groups",
      "get-/groups/{id}/hooks/{hook_id}"
    ],
    [
      "post-/groups",
      "get-/groups/{id}/hooks/{hook_id}"
    ]
  ],
  "post-/groups/{id}/share": [
    [
      "get-/groups"
    ],
    [
      "post-/groups"
    ]
  ],
  "get-/groups/{id}/projects": [
    [
      "get-/groups",
      "post-/groups/{id}/share"
    ],
    [
      "post-/groups",
      "post-/groups/{id}/share"
    ]
  ],
  "delete-/groups/{id}/hooks/{hook_id}": [
    [
      "get-/groups",
      "get-/groups/{id}/hooks/{hook_id}"
    ],
    [
      "post-/groups",
      "get-/groups/{id}/hooks/{hook_id}"
    ]
  ],
  "post-/groups": [],
  "put-/groups/{id}/hooks/{hook_id}": [
    [
      "get-/groups",
      "get-/groups/{id}/hooks/{hook_id}"
    ],
    [
      "post-/groups",
      "get-/groups/{id}/hooks/{hook_id}"
    ]
  ]
}